{
  "monday": [
    {
      "number": 3,
      "isAlternative": false,
      "pairs": {
        "top": {
          "name": "ЭЛЕКТИВНЫЕ КУРСЫ ПО ФИЗИЧЕСКОЙ КУЛЬТУРЕ И СПОРТУ",
          "type": "prac",
          "place": "Спорт. площадка ФТИ",
          "teacher": "Шишкану А.Н., Захаревич А.В."
        },
        "bottom": null
      }
    },
    {
      "number": 4,
      "isAlternative": false,
      "pairs": {
        "top": {
          "name": "ОСНОВЫ ПОЛИТИЧЕСКОЙ ВЛАСТИ",
          "type": "lec",
          "place": "215А",
          "teacher": "Бадян В.И."
        },
        "bottom": null
      }
    },
    {
      "number": 5,
      "isAlternative": false,
      "pairs": {
        "top": {
          "name": "ПОСТРОЕНИЕ И АНАЛИЗ АЛГОРИТМОВ",
          "type": "prac",
          "place": "305А",
          "teacher": "Калинкова Е.В."
        },
        "bottom": null
      }
    },
    {
      "number": 6,
      "isAlternative": true,
      "pairs": {
        "top": null,
        "bottom": {
          "name": "ОСНОВЫ ПОЛИТИЧЕСКОЙ ВЛАСТИ",
          "type": "prac",
          "place": "215А",
          "teacher": "Бадян В.И."
        }
      }
    }
  ],
  "tuesday": [
    {
      "number": 3,
      "isAlternative": false,
      "pairs": {
        "top": {
          "name": "ЭЛЕКТИВНЫЕ КУРСЫ ПО ФИЗИЧЕСКОЙ КУЛЬТУРЕ И СПОРТУ",
          "type": "prac",
          "place": "Спорт. площадка ФТИ",
          "teacher": "Шишкану А.Н., Захаревич А.В."
        },
        "bottom": null
      }
    },
    {
      "number": 4,
      "isAlternative": false,
      "pairs": {
        "top": {
          "name": "ЯЗЫКИ И МЕТОДЫ ПРОГРАММИРОВАНИЯ (ПРАКТИКУМ НА ЭВМ)",
          "type": "lab",
          "place": "305А",
          "teacher": "Марков Д.А."
        },
        "bottom": null
      }
    },
    {
      "number": 5,
      "isAlternative": false,
      "pairs": {
        "top": {
          "name": "ФИЛОСОФИЯ",
          "type": "lec",
          "place": "215А",
          "teacher": "Орлова Г.В."
        },
        "bottom": null
      }
    },
    {
      "number": 6,
      "isAlternative": true,
      "pairs": {
        "top": {
          "name": "ОПЕРАЦИОННЫЕ СИСТЕМЫ",
          "type": "lec",
          "place": "305А",
          "teacher": "Васильев В.В."
        },
        "bottom": {
          "name": "ПОСТРОЕНИЕ И АНАЛИЗ АЛГОРИТМОВ",
          "type": "lab",
          "place": "204А",
          "teacher": "Калинкова Е.В."
        }
      }
    },
    {
      "number": 7,
      "isAlternative": true,
      "pairs": {
        "top": {
          "name": "ФИЛОСОФИЯ",
          "type": "prac",
          "place": "211А",
          "teacher": "Орлова Г.В."
        },
        "bottom": {
          "name": "ПОСТРОЕНИЕ И АНАЛИЗ АЛГОРИТМОВ",
          "type": "lec",
          "place": "305А",
          "teacher": "Калинкова Е.В."
        }
      }
    }
  ],
  "wednesday": [
    {
      "number": 5,
      "isAlternative": false,
      "pairs": {
        "top": {
          "name": "БЕЗОПАСНОСТЬ ЖИЗНЕДЕЯТЕЛЬНОСТИ",
          "type": "lec",
          "place": "215В",
          "teacher": "Орлов Т.В."
        },
        "bottom": null
      }
    },
    {
      "number": 6,
      "isAlternative": false,
      "pairs": {
        "top": {
          "name": "Дифференциальные уравнения",
          "type": "lec",
          "place": "Э* 221",
          "teacher": "Зинган А.П."
        },
        "bottom": null
      }
    },
    {
      "number": 7,
      "isAlternative": false,
      "pairs": {
        "top": {
          "name": "Дифференциальные уравнения",
          "type": "prac",
          "place": "Э* 221",
          "teacher": "Зинган А.П."
        },
        "bottom": null
      }
    }
  ],
  "thursday": [
    {
      "number": 4,
      "isAlternative": false,
      "pairs": {
        "top": {
          "name": "Дифференциальные уравнения",
          "type": "prac",
          "place": "Э* 225",
          "teacher": "Зинган А.П."
        },
        "bottom": null
      }
    },
    {
      "number": 5,
      "isAlternative": false,
      "pairs": {
        "top": {
          "name": "ТЕОРИЯ ВЕРОЯТНОСТЕЙ И МАТЕМАТИЧЕСКАЯ СТАТИСТИКА",
          "type": "lec",
          "place": "Э* 114",
          "teacher": "Запольская О.Ю."
        },
        "bottom": null
      }
    },
    {
      "number": 6,
      "isAlternative": false,
      "pairs": {
        "top": {
          "name": "ОПЕРАЦИОННЫЕ СИСТЕМЫ",
          "type": "lec",
          "place": "305А",
          "teacher": "Васильев В.В."
        },
        "bottom": null
      }
    }
  ],
  "friday": [
    {
      "number": 3,
      "isAlternative": false,
      "pairs": {
        "top": {
          "name": "ЯЗЫКИ И МЕТОДЫ ПРОГРАММИРОВАНИЯ (ПРАКТИКУМ НА ЭВМ)",
          "type": "prac",
          "place": "303А",
          "teacher": "Марков Д.А."
        },
        "bottom": null
      }
    },
    {
      "number": 4,
      "isAlternative": false,
      "pairs": {
        "top": {
          "name": "Английский язык в профессиональной деятельности",
          "type": "prac",
          "place": "202А",
          "teacher": "Жосан Д.К."
        },
        "bottom": null
      }
    },
    {
      "number": 5,
      "isAlternative": false,
      "pairs": {
        "top": {
          "name": "БЕЗОПАСНОСТЬ ЖИЗНЕДЕЯТЕЛЬНОСТИ",
          "type": "prac",
          "place": "215В",
          "teacher": "Капитанчук Д.М."
        },
        "bottom": null
      }
    }
  ],
  "saturday": [
    {
      "number": 2,
      "isAlternative": false,
      "pairs": {
        "top": {
          "name": "ТЕОРИЯ ВЕРОЯТНОСТЕЙ И МАТЕМАТИЧЕСКАЯ СТАТИСТИКА",
          "type": "prac",
          "place": "Э* 113",
          "teacher": "Запольская О.Ю."
        },
        "bottom": null
      }
    },
    {
      "number": 3,
      "isAlternative": false,
      "pairs": {
        "top": {
          "name": "ДИСКРЕТНАЯ МАТЕМАТИКА",
          "type": "prac",
          "place": "Э* 3",
          "teacher": "Старчук А.С."
        },
        "bottom": null
      }
    },
    {
      "number": 4,
      "isAlternative": true,
      "pairs": {
        "top": {
          "name": "ДИСКРЕТНАЯ МАТЕМАТИКА",
          "type": "lec",
          "place": "Э* 3",
          "teacher": "Старчук А.С."
        },
        "bottom": null
      }
    }
  ]
}